odoo/addons/endpoint_product_catalog/README.rst
odoo/addons/endpoint_product_catalog/__init__.py
odoo/addons/endpoint_product_catalog/__manifest__.py
odoo/addons/endpoint_product_catalog/i18n/endpoint_product_catalog.pot
odoo/addons/endpoint_product_catalog/i18n/it.po
odoo/addons/endpoint_product_catalog/models/__init__.py
odoo/addons/endpoint_product_catalog/models/endpoint_endpoint.py
odoo/addons/endpoint_product_catalog/models/ir_filters.py
odoo/addons/endpoint_product_catalog/readme/CONTRIBUTORS.rst
odoo/addons/endpoint_product_catalog/readme/DESCRIPTION.rst
odoo/addons/endpoint_product_catalog/readme/USAGE.rst
odoo/addons/endpoint_product_catalog/static/description/icon.png
odoo/addons/endpoint_product_catalog/static/description/index.html
odoo/addons/endpoint_product_catalog/views/endpoint_endpoint.xml
odoo/addons/endpoint_product_catalog/views/ir_filters.xml
odoo14_addon_endpoint_product_catalog-14.0.1.1.0.dist-info/METADATA
odoo14_addon_endpoint_product_catalog-14.0.1.1.0.dist-info/WHEEL
odoo14_addon_endpoint_product_catalog-14.0.1.1.0.dist-info/top_level.txt
odoo14_addon_endpoint_product_catalog-14.0.1.1.0.dist-info/RECORD
