Metadata-Version: 2.1
Name: odoo14-addon-endpoint_product_catalog
Version: 14.0.1.1.0
Summary: Handle endpoints for product catalogs
Home-page: https://github.com/OCA/web-api-contrib
Author: Camptocamp, Odoo Community Association (OCA)
Author-email: support@odoo-community.org
License: AGPL-3
Classifier: Programming Language :: Python
Classifier: Framework :: Odoo
Classifier: Framework :: Odoo :: 14.0
Classifier: License :: OSI Approved :: GNU Affero General Public License v3
Requires-Python: >=3.6
Requires-Dist: odoo14-addon-endpoint
Requires-Dist: odoo14-addon-product-assortment
Requires-Dist: odoo<14.1dev,>=14.0a
